[
  {
    "登记证号": "PD20151997",
    "农药名称": "戊唑·醚菌酯",
    "农药类别": "杀菌剂",
    "剂型": "水分散粒剂",
    "总含量": "70%",
    "有效期至": "2030-8-30",
    "登记证持有人": "陕西康禾立丰生物科技药业有限公司",
    "pd_id": "dfc6f93aadaa47ffa7b4ae43d1713aeb",
    "有效成分信息": [
      {
        "有效成分": "醚菌酯",
        "有效成分英文名": "kresoxim-methyl",
        "有效成分含量": "20%"
      },
      {
        "有效成分": "戊唑醇",
        "有效成分英文名": "tebuconazole",
        "有效成分含量": "50%"
      }
    ],
    "登记证信息": {
      "登记证号": "PD20151997",
      "首次批准日期": "Aug 31, 2015",
      "有效期至": "Aug 30, 2030",
      "农药名称": "戊唑·醚菌酯",
      "毒性": "低毒",
      "剂型": "水分散粒剂",
      "登记证持有人": "陕西康禾立丰生物科技药业有限公司",
      "农药类别": "杀菌剂",
      "总有效成分含量": "70%",
      "备注": ""
    },
    "制剂用药量信息": [
      
      {
        "作物/场所": "苹果树",
        "防治对象": "斑点落叶病",
        "用药量": "6000-8000倍液",
        "施用方法": "喷雾"
      }
    ]
  },
  {
    "登记证号": "PD20151996",
    "农药名称": "吡嘧磺隆",
    "农药类别": "除草剂",
    "剂型": "可湿性粉剂",
    "总含量": "10%",
    "有效期至": "2030-8-30",
    "登记证持有人": "江西巴菲特化工有限公司",
    "pd_id": "7ded33484acf442eb37137df142d6e48",
    "有效成分信息": [
      {
        "有效成分": "吡嘧磺隆",
        "有效成分英文名": "pyrazosulfuron-ethyl",
        "有效成分含量": "10%"
      }
    ],
    "登记证信息": {
      "登记证号": "PD20151996",
      "首次批准日期": "Aug 31, 2015",
      "有效期至": "Aug 30, 2030",
      "农药名称": "吡嘧磺隆",
      "毒性": "低毒",
      "剂型": "可湿性粉剂",
      "登记证持有人": "江西巴菲特化工有限公司",
      "农药类别": "除草剂",
      "总有效成分含量": "10%",
      "备注": ""
    },
    "制剂用药量信息": [
      
      {
        "作物/场所": "移栽水稻田",
        "防治对象": "稗草、莎草及阔叶杂草",
        "用药量": "10-20克/亩",
        "施用方法": "药土法"
      }
    ]
  },
  {
    "登记证号": "PD20151995",
    "农药名称": "螺螨酯",
    "农药类别": "杀螨剂",
    "剂型": "悬浮剂",
    "总含量": "40%",
    "有效期至": "2030-8-30",
    "登记证持有人": "江西巴菲特化工有限公司",
    "pd_id": "ad130b1bc63449ee8fa4958bfe6a2b38",
    "有效成分信息": [
      {
        "有效成分": "螺螨酯",
        "有效成分英文名": "spirodiclofen",
        "有效成分含量": "40%"
      }
    ],
    "登记证信息": {
      "登记证号": "PD20151995",
      "首次批准日期": "Aug 31, 2015",
      "有效期至": "Aug 30, 2030",
      "农药名称": "螺螨酯",
      "毒性": "低毒",
      "剂型": "悬浮剂",
      "登记证持有人": "江西巴菲特化工有限公司",
      "农药类别": "杀螨剂",
      "总有效成分含量": "40%",
      "备注": ""
    },
    "制剂用药量信息": [
      
      {
        "作物/场所": "柑橘树",
        "防治对象": "红蜘蛛",
        "用药量": "6667-10000倍液",
        "施用方法": "喷雾"
      }
    ]
  },
  {
    "登记证号": "WP20150178",
    "农药名称": "苏云金杆菌(以色列亚种)",
    "农药类别": "卫生杀虫剂",
    "剂型": "可湿性粉剂",
    "总含量": "1600ITU/毫克",
    "有效期至": "2030-8-29",
    "登记证持有人": "江苏省扬州绿源生物化工有限公司",
    "pd_id": "808e2cb6d8bb4c6db9d120054b3d049e",
    "有效成分信息": [
      {
        "有效成分": "苏云金杆菌(以色列亚种)",
        "有效成分英文名": "bacillus thuringiensis H-14",
        "有效成分含量": "1600ITU/毫克"
      }
    ],
    "登记证信息": {
      "登记证号": "WP20150178",
      "首次批准日期": "Aug 30, 2015",
      "有效期至": "Aug 29, 2030",
      "农药名称": "苏云金杆菌(以色列亚种)",
      "毒性": "低毒",
      "剂型": "可湿性粉剂",
      "登记证持有人": "江苏省扬州绿源生物化工有限公司",
      "农药类别": "卫生杀虫剂",
      "总有效成分含量": "1600ITU/毫克",
      "备注": ""
    },
    "制剂用药量信息": [
      
      {
        "作物/场所": "室外",
        "防治对象": "蚊(幼虫)",
        "用药量": "1-2克/平方米",
        "施用方法": "喷洒"
      }
    ]
  },
  {
    "登记证号": "WP20150175",
    "农药名称": "杀蟑胶饵",
    "农药类别": "卫生杀虫剂",
    "剂型": "胶饵",
    "总含量": "0.05%",
    "有效期至": "2030-8-29",
    "登记证持有人": "辽宁省沈阳爱威科技发展股份有限公司",
    "pd_id": "cf471771c4824764abd39ecd27827cc7",
    "有效成分信息": [
      {
        "有效成分": "氟虫腈",
        "有效成分英文名": "fipronil",
        "有效成分含量": "0.05%"
      }
    ],
    "登记证信息": {
      "登记证号": "WP20150175",
      "首次批准日期": "Aug 30, 2015",
      "有效期至": "Aug 29, 2030",
      "农药名称": "杀蟑胶饵",
      "毒性": "低毒",
      "剂型": "胶饵",
      "登记证持有人": "辽宁省沈阳爱威科技发展股份有限公司",
      "农药类别": "卫生杀虫剂",
      "总有效成分含量": "0.05%",
      "备注": ""
    },
    "制剂用药量信息": [
      
      {
        "作物/场所": "室内",
        "防治对象": "蜚蠊",
        "用药量": "/",
        "施用方法": "投饵"
      }
    ]
  },
  {
    "登记证号": "WP20150173",
    "农药名称": "杀蝇饵剂",
    "农药类别": "卫生杀虫剂",
    "剂型": "饵剂",
    "总含量": "1%",
    "有效期至": "2030-8-29",
    "登记证持有人": "绩溪县庆丰天鹰生化有限公司",
    "pd_id": "a02d99099994430999e9a071c5df92b4",
    "有效成分信息": [
      {
        "有效成分": "甲基吡噁磷",
        "有效成分英文名": "azamethiphos",
        "有效成分含量": "1%"
      }
    ],
    "登记证信息": {
      "登记证号": "WP20150173",
      "首次批准日期": "Aug 30, 2015",
      "有效期至": "Aug 29, 2030",
      "农药名称": "杀蝇饵剂",
      "毒性": "微毒",
      "剂型": "饵剂",
      "登记证持有人": "绩溪县庆丰天鹰生化有限公司",
      "农药类别": "卫生杀虫剂",
      "总有效成分含量": "1%",
      "备注": "2022年09月03日，变更原持有人河北国欣诺农生物技术有限公司。"
    },
    "制剂用药量信息": [
      
      {
        "作物/场所": "室内",
        "防治对象": "蝇",
        "用药量": "/",
        "施用方法": "投放"
      }
    ]
  },
  {
    "登记证号": "WP20150172",
    "农药名称": "电热蚊香液",
    "农药类别": "卫生杀虫剂",
    "剂型": "电热蚊香液",
    "总含量": "1%",
    "有效期至": "2030-8-29",
    "登记证持有人": "四川省成都彩虹电器(集团)股份有限公司",
    "pd_id": "699d77507a43469eabb097c5a0d8daad",
    "有效成分信息": [
      {
        "有效成分": "氯氟醚菊酯",
        "有效成分英文名": "meperfluthrin",
        "有效成分含量": "1%"
      }
    ],
    "登记证信息": {
      "登记证号": "WP20150172",
      "首次批准日期": "Aug 30, 2015",
      "有效期至": "Aug 29, 2030",
      "农药名称": "电热蚊香液",
      "毒性": "微毒",
      "剂型": "电热蚊香液",
      "登记证持有人": "四川省成都彩虹电器(集团)股份有限公司",
      "农药类别": "卫生杀虫剂",
      "总有效成分含量": "1%",
      "备注": ""
    },
    "制剂用药量信息": [
      
      {
        "作物/场所": "室内",
        "防治对象": "蚊",
        "用药量": "/",
        "施用方法": "电热加温"
      }
    ]
  },
  {
    "登记证号": "PD20151993",
    "农药名称": "丁硫克百威",
    "农药类别": "杀虫剂",
    "剂型": "乳油",
    "总含量": "200克/升",
    "有效期至": "2030-8-29",
    "登记证持有人": "江苏蓝丰生物化工有限公司",
    "pd_id": "c69fe62ae7db47c797df25c6e29ccf69",
    "有效成分信息": [
      {
        "有效成分": "丁硫克百威",
        "有效成分英文名": "carbosulfan",
        "有效成分含量": "200克/升"
      }
    ],
    "登记证信息": {
      "登记证号": "PD20151993",
      "首次批准日期": "Aug 30, 2015",
      "有效期至": "Aug 29, 2030",
      "农药名称": "丁硫克百威",
      "毒性": "中等毒",
      "剂型": "乳油",
      "登记证持有人": "江苏蓝丰生物化工有限公司",
      "农药类别": "杀虫剂",
      "总有效成分含量": "200克/升",
      "备注": "2025年4月23日，变更原持有人江苏蓝丰生物化工股份有限公司。"
    },
    "制剂用药量信息": [
      
      {
        "作物/场所": "棉花",
        "防治对象": "蚜虫",
        "用药量": "45-60毫升/亩",
        "施用方法": "喷雾"
      }
    ]
  },
  {
    "登记证号": "PD20151990",
    "农药名称": "甲氨基阿维菌素苯甲酸盐",
    "农药类别": "杀虫剂",
    "剂型": "水分散粒剂",
    "总含量": "5%",
    "有效期至": "2030-8-29",
    "登记证持有人": "河北中保绿农作物科技有限公司",
    "pd_id": "2e0c8e6811fd4202a2df344339b534aa",
    "有效成分信息": [
      {
        "有效成分": "甲氨基阿维菌素",
        "有效成分英文名": "abamectin-aminomethyl",
        "有效成分含量": "5%"
      }
    ],
    "登记证信息": {
      "登记证号": "PD20151990",
      "首次批准日期": "Aug 30, 2015",
      "有效期至": "Aug 29, 2030",
      "农药名称": "甲氨基阿维菌素苯甲酸盐",
      "毒性": "低毒",
      "剂型": "水分散粒剂",
      "登记证持有人": "河北中保绿农作物科技有限公司",
      "农药类别": "杀虫剂",
      "总有效成分含量": "5%",
      "备注": "甲氨基阿维菌素苯甲酸盐含量：5.7%。"
    },
    "制剂用药量信息": [
      
      {
        "作物/场所": "甘蓝",
        "防治对象": "小菜蛾",
        "用药量": "4-5克/亩",
        "施用方法": "喷雾"
      }
    ]
  },
  {
    "登记证号": "PD20151988",
    "农药名称": "三氯吡氧乙酸",
    "农药类别": "除草剂",
    "剂型": "原药",
    "总含量": "98%",
    "有效期至": "2030-8-29",
    "登记证持有人": "利尔化学股份有限公司",
    "pd_id": "b650914a4c114da19205d14a1b4db584",
    "有效成分信息": [
      {
        "有效成分": "三氯吡氧乙酸",
        "有效成分英文名": "triclopyr",
        "有效成分含量": "98%"
      }
    ],
    "登记证信息": {
      "登记证号": "PD20151988",
      "首次批准日期": "Aug 30, 2015",
      "有效期至": "Aug 29, 2030",
      "农药名称": "三氯吡氧乙酸",
      "毒性": "低毒",
      "剂型": "原药",
      "登记证持有人": "利尔化学股份有限公司",
      "农药类别": "除草剂",
      "总有效成分含量": "98%",
      "备注": ""
    },
    "制剂用药量信息": [
      
    ]
  },
  {
    "登记证号": "PD20151986",
    "农药名称": "苏云金杆菌",
    "农药类别": "杀虫剂",
    "剂型": "可湿性粉剂",
    "总含量": "32000IU/毫克",
    "有效期至": "2030-8-29",
    "登记证持有人": "江苏省扬州绿源生物化工有限公司",
    "pd_id": "fa008e2a007645ddbb5b74b68e7fced6",
    "有效成分信息": [
      {
        "有效成分": "苏云金杆菌",
        "有效成分英文名": "bacillus thuringiensis",
        "有效成分含量": "32000IU/毫克"
      }
    ],
    "登记证信息": {
      "登记证号": "PD20151986",
      "首次批准日期": "Aug 30, 2015",
      "有效期至": "Aug 29, 2030",
      "农药名称": "苏云金杆菌",
      "毒性": "微毒",
      "剂型": "可湿性粉剂",
      "登记证持有人": "江苏省扬州绿源生物化工有限公司",
      "农药类别": "杀虫剂",
      "总有效成分含量": "32000IU/毫克",
      "备注": "2024年4月28日，增加豇豆豆荚螟。"
    },
    "制剂用药量信息": [
      
      {
        "作物/场所": "枇杷树",
        "防治对象": "黄毛虫",
        "用药量": "稀释1600-2000倍液",
        "施用方法": "喷雾"
      },
      {
        "作物/场所": "桃树",
        "防治对象": "梨小食心虫",
        "用药量": "200-400倍制剂",
        "施用方法": "喷雾"
      },
      {
        "作物/场所": "甘蓝",
        "防治对象": "小菜蛾",
        "用药量": "30-50克",
        "施用方法": "喷雾"
      },
      {
        "作物/场所": "花椰菜",
        "防治对象": "菜青虫",
        "用药量": "100-125克/亩",
        "施用方法": "喷雾"
      },
      {
        "作物/场所": "豇豆",
        "防治对象": "豆荚螟",
        "用药量": "100克/亩",
        "施用方法": "喷雾"
      }
    ]
  },
  {
    "登记证号": "PD20151984",
    "农药名称": "阿维菌素",
    "农药类别": "杀虫剂",
    "剂型": "悬浮剂",
    "总含量": "5%",
    "有效期至": "2030-8-29",
    "登记证持有人": "河北三农农用化工有限公司",
    "pd_id": "ece862300f3f4ac1bd05f2dee0155eb7",
    "有效成分信息": [
      {
        "有效成分": "阿维菌素",
        "有效成分英文名": "abamectin",
        "有效成分含量": "5%"
      }
    ],
    "登记证信息": {
      "登记证号": "PD20151984",
      "首次批准日期": "Aug 30, 2015",
      "有效期至": "Aug 29, 2030",
      "农药名称": "阿维菌素",
      "毒性": "低毒(原药高毒)",
      "剂型": "悬浮剂",
      "登记证持有人": "河北三农农用化工有限公司",
      "农药类别": "杀虫剂",
      "总有效成分含量": "5%",
      "备注": ""
    },
    "制剂用药量信息": [
      
      {
        "作物/场所": "水稻",
        "防治对象": "稻纵卷叶螟",
        "用药量": "12-20毫升/亩",
        "施用方法": "喷雾"
      }
    ]
  },
  {
    "登记证号": "PD20151983",
    "农药名称": "草甘膦铵盐",
    "农药类别": "除草剂",
    "剂型": "可溶粒剂",
    "总含量": "80%",
    "有效期至": "2030-8-29",
    "登记证持有人": "河北三农农用化工有限公司",
    "pd_id": "4bce1e6cb5574b26b9a306c2d05829cd",
    "有效成分信息": [
      {
        "有效成分": "草甘膦",
        "有效成分英文名": "glyphosate",
        "有效成分含量": "80%"
      }
    ],
    "登记证信息": {
      "登记证号": "PD20151983",
      "首次批准日期": "Aug 30, 2015",
      "有效期至": "Aug 29, 2030",
      "农药名称": "草甘膦铵盐",
      "毒性": "低毒",
      "剂型": "可溶粒剂",
      "登记证持有人": "河北三农农用化工有限公司",
      "农药类别": "除草剂",
      "总有效成分含量": "80%",
      "备注": "草甘膦铵盐含量：88.8%。"
    },
    "制剂用药量信息": [
      
      {
        "作物/场所": "柑橘园",
        "防治对象": "杂草",
        "用药量": "93.75-187.5克/亩",
        "施用方法": "定向茎叶喷雾"
      }
    ]
  },
  {
    "登记证号": "PD20151979",
    "农药名称": "稻丰散",
    "农药类别": "杀虫剂",
    "剂型": "乳油",
    "总含量": "60%",
    "有效期至": "2030-8-29",
    "登记证持有人": "江苏腾龙生物药业有限公司",
    "pd_id": "3b1b85969bf94b6897b20586a4b82554",
    "有效成分信息": [
      {
        "有效成分": "稻丰散",
        "有效成分英文名": "phenthoate",
        "有效成分含量": "60%"
      }
    ],
    "登记证信息": {
      "登记证号": "PD20151979",
      "首次批准日期": "Aug 30, 2015",
      "有效期至": "Aug 29, 2030",
      "农药名称": "稻丰散",
      "毒性": "中等毒",
      "剂型": "乳油",
      "登记证持有人": "江苏腾龙生物药业有限公司",
      "农药类别": "杀虫剂",
      "总有效成分含量": "60%",
      "备注": ""
    },
    "制剂用药量信息": [
      
      {
        "作物/场所": "水稻",
        "防治对象": "二化螟",
        "用药量": "60-100毫升/亩",
        "施用方法": "喷雾"
      },
      {
        "作物/场所": "水稻",
        "防治对象": "稻纵卷叶螟",
        "用药量": "60-100毫升/亩",
        "施用方法": "喷雾"
      }
    ]
  },
  {
    "登记证号": "PD20151975",
    "农药名称": "氧氟·甲戊灵",
    "农药类别": "除草剂",
    "剂型": "乳油",
    "总含量": "34%",
    "有效期至": "2030-8-29",
    "登记证持有人": "青岛现代农化有限公司",
    "pd_id": "4e5ac67f6fff4c49b1ad9401e34d8f81",
    "有效成分信息": [
      {
        "有效成分": "乙氧氟草醚",
        "有效成分英文名": "oxyfluorfen",
        "有效成分含量": "14%"
      },
      {
        "有效成分": "二甲戊灵",
        "有效成分英文名": "pendimethalin",
        "有效成分含量": "20%"
      }
    ],
    "登记证信息": {
      "登记证号": "PD20151975",
      "首次批准日期": "Aug 30, 2015",
      "有效期至": "Aug 29, 2030",
      "农药名称": "氧氟·甲戊灵",
      "毒性": "低毒",
      "剂型": "乳油",
      "登记证持有人": "青岛现代农化有限公司",
      "农药类别": "除草剂",
      "总有效成分含量": "34%",
      "备注": "2023年7月9日，变更原持有人山东省青岛现代农化有限公司。"
    },
    "制剂用药量信息": [
      
      {
        "作物/场所": "水稻移栽田",
        "防治对象": "一年生杂草",
        "用药量": "25-40毫升/亩",
        "施用方法": "药土法"
      }
    ]
  },
  {
    "登记证号": "PD20151974",
    "农药名称": "多抗·己唑醇",
    "农药类别": "杀菌剂",
    "剂型": "悬浮剂",
    "总含量": "10%",
    "有效期至": "2030-8-29",
    "登记证持有人": "燕化永乐（乐亭）生物科技有限公司",
    "pd_id": "139d0cfadb75423987705dc87ed65220",
    "有效成分信息": [
      {
        "有效成分": "己唑醇",
        "有效成分英文名": "hexaconazole",
        "有效成分含量": "5%"
      },
      {
        "有效成分": "多抗霉素B",
        "有效成分英文名": "polyoxin B",
        "有效成分含量": "5%"
      }
    ],
    "登记证信息": {
      "登记证号": "PD20151974",
      "首次批准日期": "Aug 30, 2015",
      "有效期至": "Aug 29, 2030",
      "农药名称": "多抗·己唑醇",
      "毒性": "低毒",
      "剂型": "悬浮剂",
      "登记证持有人": "燕化永乐（乐亭）生物科技有限公司",
      "农药类别": "杀菌剂",
      "总有效成分含量": "10%",
      "备注": ""
    },
    "制剂用药量信息": [
      
      {
        "作物/场所": "苹果树",
        "防治对象": "斑点落叶病",
        "用药量": "1428-2000倍液",
        "施用方法": "喷雾"
      }
    ]
  },
  {
    "登记证号": "PD20151972",
    "农药名称": "丙炔氟草胺",
    "农药类别": "除草剂",
    "剂型": "原药",
    "总含量": "99.2%",
    "有效期至": "2030-8-29",
    "登记证持有人": "山东滨农科技有限公司",
    "pd_id": "acfae5b7489e467e9c2203dd25cbc962",
    "有效成分信息": [
      {
        "有效成分": "丙炔氟草胺",
        "有效成分英文名": "flumioxazin",
        "有效成分含量": "99.2%"
      }
    ],
    "登记证信息": {
      "登记证号": "PD20151972",
      "首次批准日期": "Aug 30, 2015",
      "有效期至": "Aug 29, 2030",
      "农药名称": "丙炔氟草胺",
      "毒性": "低毒",
      "剂型": "原药",
      "登记证持有人": "山东滨农科技有限公司",
      "农药类别": "除草剂",
      "总有效成分含量": "99.2%",
      "备注": ""
    },
    "制剂用药量信息": [
      
    ]
  },
  {
    "登记证号": "PD20151971",
    "农药名称": "啶虫脒",
    "农药类别": "杀虫剂",
    "剂型": "乳油",
    "总含量": "5%",
    "有效期至": "2030-8-29",
    "登记证持有人": "南通金陵农化有限公司",
    "pd_id": "f13698bf2aa74dcd855e6ceeda15baec",
    "有效成分信息": [
      {
        "有效成分": "啶虫脒",
        "有效成分英文名": "acetamiprid",
        "有效成分含量": "5%"
      }
    ],
    "登记证信息": {
      "登记证号": "PD20151971",
      "首次批准日期": "Aug 30, 2015",
      "有效期至": "Aug 29, 2030",
      "农药名称": "啶虫脒",
      "毒性": "低毒",
      "剂型": "乳油",
      "登记证持有人": "南通金陵农化有限公司",
      "农药类别": "杀虫剂",
      "总有效成分含量": "5%",
      "备注": ""
    },
    "制剂用药量信息": [
      
      {
        "作物/场所": "柑橘树",
        "防治对象": "蚜虫",
        "用药量": "2000-3000倍液",
        "施用方法": "喷雾"
      }
    ]
  },
  {
    "登记证号": "PD20151970",
    "农药名称": "氟硅唑",
    "农药类别": "杀菌剂",
    "剂型": "水乳剂",
    "总含量": "10%",
    "有效期至": "2030-8-29",
    "登记证持有人": "河南中天恒信生物化学科技有限公司",
    "pd_id": "0abadd770820424d8e98bf0c668fc68c",
    "有效成分信息": [
      {
        "有效成分": "氟硅唑",
        "有效成分英文名": "flusilazole",
        "有效成分含量": "10%"
      }
    ],
    "登记证信息": {
      "登记证号": "PD20151970",
      "首次批准日期": "Aug 30, 2015",
      "有效期至": "Aug 29, 2030",
      "农药名称": "氟硅唑",
      "毒性": "低毒",
      "剂型": "水乳剂",
      "登记证持有人": "河南中天恒信生物化学科技有限公司",
      "农药类别": "杀菌剂",
      "总有效成分含量": "10%",
      "备注": ""
    },
    "制剂用药量信息": [
      
      {
        "作物/场所": "梨树",
        "防治对象": "黑星病",
        "用药量": "2000-2500倍液",
        "施用方法": "喷雾"
      }
    ]
  },
  {
    "登记证号": "PD20151969",
    "农药名称": "乙羧氟草醚",
    "农药类别": "除草剂",
    "剂型": "乳油",
    "总含量": "20%",
    "有效期至": "2030-8-29",
    "登记证持有人": "广西德丰富化工有限责任公司",
    "pd_id": "73914f47f4454733a95c292f0640b102",
    "有效成分信息": [
      {
        "有效成分": "乙羧氟草醚",
        "有效成分英文名": "fluoroglycofen-ethyl",
        "有效成分含量": "20%"
      }
    ],
    "登记证信息": {
      "登记证号": "PD20151969",
      "首次批准日期": "Aug 30, 2015",
      "有效期至": "Aug 29, 2030",
      "农药名称": "乙羧氟草醚",
      "毒性": "低毒",
      "剂型": "乳油",
      "登记证持有人": "广西德丰富化工有限责任公司",
      "农药类别": "除草剂",
      "总有效成分含量": "20%",
      "备注": "2022年12月30日，变更原持有人南宁市德丰富化工有限责任公司。"
    },
    "制剂用药量信息": [
      
      {
        "作物/场所": "花生田",
        "防治对象": "一年生阔叶杂草",
        "用药量": "20-30毫升/亩",
        "施用方法": "茎叶喷雾"
      }
    ]
  }
]